csrlite/__init__.py
csrlite/ae/__init__.py
csrlite/ae/ae_listing.py
csrlite/ae/ae_specific.py
csrlite/ae/ae_summary.py
csrlite/ae/ae_utils.py
csrlite/cm/cm_listing.py
csrlite/cm/cm_summary.py
csrlite/common/config.py
csrlite/common/count.py
csrlite/common/parse.py
csrlite/common/plan.py
csrlite/common/rtf.py
csrlite/common/utils.py
csrlite/common/yaml_loader.py
csrlite/disposition/__init__.py
csrlite/disposition/disposition.py
csrlite/ie/ie_listing.py
csrlite/ie/ie_summary.py
csrlite/mh/mh_listing.py
csrlite/mh/mh_summary.py
csrlite/pd/pd_listing.py
csrlite-0.3.0.dist-info/METADATA
csrlite-0.3.0.dist-info/WHEEL
csrlite-0.3.0.dist-info/top_level.txt
csrlite-0.3.0.dist-info/RECORD
